{"created_at":"Mon Nov 01 19:57:09 +0000 2021","id":1455262657427218438,"id_str":"1455262657427218438","text":"RT @SummerShikwane: Please retweet for awareness! https:\/\/t.co\/iC3kClIMDS","source":"\u003ca href=\"http:\/\/twitter.com\/download\/iphone\" rel=\"nofollow\"\u003eTwitter for iPhone\u003c\/a\u003e","truncated":false,"in_reply_to_status_id":null,"in_reply_to_status_id_str":null,"in_reply_to_user_id":null,"in_reply_to_user_id_str":null,"in_reply_to_screen_name":null,"user":{"id":800921959,"id_str":"800921959","name":"YOMBO","screen_name":"dhammyshow","location":"Lagos","url":"http:\/\/www.hipnaija.com","description":"God, Clothier, Man utd \ud83d\udd34","translator_type":"none","protected":false,"verified":false,"followers_count":9610,"friends_count":9561,"listed_count":1,"favourites_count":106416,"statuses_count":39132,"created_at":"Mon Sep 03 18:12:26 +0000 2012","utc_offset":null,"time_zone":null,"geo_enabled":false,"lang":null,"contributors_enabled":false,"is_translator":false,"profile_background_color":"C0DEED","profile_background_image_url":"http:\/\/abs.twimg.com\/images\/themes\/theme1\/bg.png","profile_background_image_url_https":"https:\/\/abs.twimg.com\/images\/themes\/theme1\/bg.png","profile_background_tile":false,"profile_link_color":"1DA1F2","profile_sidebar_border_color":"C0DEED","profile_sidebar_fill_color":"DDEEF6","profile_text_color":"333333","profile_use_background_image":true,"profile_image_url":"http:\/\/pbs.twimg.com\/profile_images\/1318667266851020803\/0sgCNOGd_normal.jpg","profile_image_url_https":"https:\/\/pbs.twimg.com\/profile_images\/1318667266851020803\/0sgCNOGd_normal.jpg","profile_banner_url":"https:\/\/pbs.twimg.com\/profile_banners\/800921959\/1603229752","default_profile":true,"default_profile_image":false,"following":null,"follow_request_sent":null,"notifications":null,"withheld_in_countries":[]},"geo":null,"coordinates":null,"place":null,"contributors":null,"retweeted_status":{"created_at":"Sun Oct 31 12:42:06 +0000 2021","id":1454790783991697408,"id_str":"1454790783991697408","text":"Please retweet for awareness! https:\/\/t.co\/iC3kClIMDS","display_text_range":[0,29],"source":"\u003ca href=\"http:\/\/twitter.com\/download\/iphone\" rel=\"nofollow\"\u003eTwitter for iPhone\u003c\/a\u003e","truncated":false,"in_reply_to_status_id":null,"in_reply_to_status_id_str":null,"in_reply_to_user_id":null,"in_reply_to_user_id_str":null,"in_reply_to_screen_name":null,"user":{"id":892100948478373890,"id_str":"892100948478373890","name":"\ud83c\udf36","screen_name":"SummerShikwane","location":"\ud83c\uddff\ud83c\udde6","url":null,"description":"\ud83d\udce5: summershikwane07@gmail.com","translator_type":"none","protected":false,"verified":false,"followers_count":12543,"friends_count":1610,"listed_count":4,"favourites_count":55317,"statuses_count":74982,"created_at":"Mon Jul 31 19:13:35 +0000 2017","utc_offset":null,"time_zone":null,"geo_enabled":true,"lang":null,"contributors_enabled":false,"is_translator":false,"profile_background_color":"F5F8FA","profile_background_image_url":"","profile_background_image_url_https":"","profile_background_tile":false,"profile_link_color":"1DA1F2","profile_sidebar_border_color":"C0DEED","profile_sidebar_fill_color":"DDEEF6","profile_text_color":"333333","profile_use_background_image":true,"profile_image_url":"http:\/\/pbs.twimg.com\/profile_images\/1439886292494471171\/66p-UdlH_normal.jpg","profile_image_url_https":"https:\/\/pbs.twimg.com\/profile_images\/1439886292494471171\/66p-UdlH_normal.jpg","profile_banner_url":"https:\/\/pbs.twimg.com\/profile_banners\/892100948478373890\/1619631273","default_profile":true,"default_profile_image":false,"following":null,"follow_request_sent":null,"notifications":null,"withheld_in_countries":[]},"geo":null,"coordinates":null,"place":null,"contributors":null,"is_quote_status":false,"quote_count":2,"reply_count":3,"retweet_count":2354,"favorite_count":503,"entities":{"hashtags":[],"urls":[],"user_mentions":[],"symbols":[],"media":[{"id":1454790753738272771,"id_str":"1454790753738272771","indices":[30,53],"media_url":"http:\/\/pbs.twimg.com\/media\/FDB0e5MXsAM1UH0.jpg","media_url_https":"https:\/\/pbs.twimg.com\/media\/FDB0e5MXsAM1UH0.jpg","url":"https:\/\/t.co\/iC3kClIMDS","display_url":"pic.twitter.com\/iC3kClIMDS","expanded_url":"https:\/\/twitter.com\/SummerShikwane\/status\/1454790783991697408\/photo\/1","type":"photo","sizes":{"thumb":{"w":150,"h":150,"resize":"crop"},"large":{"w":1170,"h":1035,"resize":"fit"},"medium":{"w":1170,"h":1035,"resize":"fit"},"small":{"w":680,"h":602,"resize":"fit"}}}]},"extended_entities":{"media":[{"id":1454790753738272771,"id_str":"1454790753738272771","indices":[30,53],"media_url":"http:\/\/pbs.twimg.com\/media\/FDB0e5MXsAM1UH0.jpg","media_url_https":"https:\/\/pbs.twimg.com\/media\/FDB0e5MXsAM1UH0.jpg","url":"https:\/\/t.co\/iC3kClIMDS","display_url":"pic.twitter.com\/iC3kClIMDS","expanded_url":"https:\/\/twitter.com\/SummerShikwane\/status\/1454790783991697408\/photo\/1","type":"photo","sizes":{"thumb":{"w":150,"h":150,"resize":"crop"},"large":{"w":1170,"h":1035,"resize":"fit"},"medium":{"w":1170,"h":1035,"resize":"fit"},"small":{"w":680,"h":602,"resize":"fit"}}}]},"favorited":false,"retweeted":false,"possibly_sensitive":false,"filter_level":"low","lang":"en"},"is_quote_status":false,"quote_count":0,"reply_count":0,"retweet_count":0,"favorite_count":0,"entities":{"hashtags":[],"urls":[],"user_mentions":[{"screen_name":"SummerShikwane","name":"\ud83c\udf36","id":892100948478373890,"id_str":"892100948478373890","indices":[3,18]}],"symbols":[],"media":[{"id":1454790753738272771,"id_str":"1454790753738272771","indices":[50,73],"media_url":"http:\/\/pbs.twimg.com\/media\/FDB0e5MXsAM1UH0.jpg","media_url_https":"https:\/\/pbs.twimg.com\/media\/FDB0e5MXsAM1UH0.jpg","url":"https:\/\/t.co\/iC3kClIMDS","display_url":"pic.twitter.com\/iC3kClIMDS","expanded_url":"https:\/\/twitter.com\/SummerShikwane\/status\/1454790783991697408\/photo\/1","type":"photo","sizes":{"thumb":{"w":150,"h":150,"resize":"crop"},"large":{"w":1170,"h":1035,"resize":"fit"},"medium":{"w":1170,"h":1035,"resize":"fit"},"small":{"w":680,"h":602,"resize":"fit"}},"source_status_id":1454790783991697408,"source_status_id_str":"1454790783991697408","source_user_id":892100948478373890,"source_user_id_str":"892100948478373890"}]},"extended_entities":{"media":[{"id":1454790753738272771,"id_str":"1454790753738272771","indices":[50,73],"media_url":"http:\/\/pbs.twimg.com\/media\/FDB0e5MXsAM1UH0.jpg","media_url_https":"https:\/\/pbs.twimg.com\/media\/FDB0e5MXsAM1UH0.jpg","url":"https:\/\/t.co\/iC3kClIMDS","display_url":"pic.twitter.com\/iC3kClIMDS","expanded_url":"https:\/\/twitter.com\/SummerShikwane\/status\/1454790783991697408\/photo\/1","type":"photo","sizes":{"thumb":{"w":150,"h":150,"resize":"crop"},"large":{"w":1170,"h":1035,"resize":"fit"},"medium":{"w":1170,"h":1035,"resize":"fit"},"small":{"w":680,"h":602,"resize":"fit"}},"source_status_id":1454790783991697408,"source_status_id_str":"1454790783991697408","source_user_id":892100948478373890,"source_user_id_str":"892100948478373890"}]},"favorited":false,"retweeted":false,"possibly_sensitive":false,"filter_level":"low","lang":"en","timestamp_ms":"1635796629660"}
