{"created_at":"Mon Nov 01 20:22:25 +0000 2021","id":1455269015992127490,"id_str":"1455269015992127490","text":"@begenius_treso Il a oubli\u00e9 sa vespa https:\/\/t.co\/WZHMCkLEWM","display_text_range":[16,36],"source":"\u003ca href=\"http:\/\/twitter.com\/download\/android\" rel=\"nofollow\"\u003eTwitter for Android\u003c\/a\u003e","truncated":false,"in_reply_to_status_id":1455268717307301889,"in_reply_to_status_id_str":"1455268717307301889","in_reply_to_user_id":1369451278015860745,"in_reply_to_user_id_str":"1369451278015860745","in_reply_to_screen_name":"begenius_treso","user":{"id":1285373291235024896,"id_str":"1285373291235024896","name":"Callux","screen_name":"BCallux","location":null,"url":"https:\/\/youtu.be\/7iHr9fMomMk","description":"Retired Legend.","translator_type":"none","protected":false,"verified":false,"followers_count":117,"friends_count":92,"listed_count":0,"favourites_count":857,"statuses_count":1503,"created_at":"Tue Jul 21 00:37:38 +0000 2020","utc_offset":null,"time_zone":null,"geo_enabled":true,"lang":null,"contributors_enabled":false,"is_translator":false,"profile_background_color":"F5F8FA","profile_background_image_url":"","profile_background_image_url_https":"","profile_background_tile":false,"profile_link_color":"1DA1F2","profile_sidebar_border_color":"C0DEED","profile_sidebar_fill_color":"DDEEF6","profile_text_color":"333333","profile_use_background_image":true,"profile_image_url":"http:\/\/pbs.twimg.com\/profile_images\/1447318032045461512\/PHlpHq3I_normal.jpg","profile_image_url_https":"https:\/\/pbs.twimg.com\/profile_images\/1447318032045461512\/PHlpHq3I_normal.jpg","profile_banner_url":"https:\/\/pbs.twimg.com\/profile_banners\/1285373291235024896\/1633902482","default_profile":true,"default_profile_image":false,"following":null,"follow_request_sent":null,"notifications":null,"withheld_in_countries":[]},"geo":null,"coordinates":null,"place":null,"contributors":null,"is_quote_status":false,"quote_count":0,"reply_count":0,"retweet_count":0,"favorite_count":0,"entities":{"hashtags":[],"urls":[],"user_mentions":[{"screen_name":"begenius_treso","name":"Treso_livesvibes","id":1369451278015860745,"id_str":"1369451278015860745","indices":[0,15]}],"symbols":[],"media":[{"id":1455269007137910794,"id_str":"1455269007137910794","indices":[37,60],"description":" ","media_url":"http:\/\/pbs.twimg.com\/tweet_video_thumb\/FDInc58XMAoO3EV.jpg","media_url_https":"https:\/\/pbs.twimg.com\/tweet_video_thumb\/FDInc58XMAoO3EV.jpg","url":"https:\/\/t.co\/WZHMCkLEWM","display_url":"pic.twitter.com\/WZHMCkLEWM","expanded_url":"https:\/\/twitter.com\/BCallux\/status\/1455269015992127490\/photo\/1","type":"photo","sizes":{"thumb":{"w":150,"h":150,"resize":"crop"},"large":{"w":480,"h":360,"resize":"fit"},"medium":{"w":480,"h":360,"resize":"fit"},"small":{"w":480,"h":360,"resize":"fit"}}}]},"extended_entities":{"media":[{"id":1455269007137910794,"id_str":"1455269007137910794","indices":[37,60],"description":" ","media_url":"http:\/\/pbs.twimg.com\/tweet_video_thumb\/FDInc58XMAoO3EV.jpg","media_url_https":"https:\/\/pbs.twimg.com\/tweet_video_thumb\/FDInc58XMAoO3EV.jpg","url":"https:\/\/t.co\/WZHMCkLEWM","display_url":"pic.twitter.com\/WZHMCkLEWM","expanded_url":"https:\/\/twitter.com\/BCallux\/status\/1455269015992127490\/photo\/1","type":"animated_gif","video_info":{"aspect_ratio":[4,3],"variants":[{"bitrate":0,"content_type":"video\/mp4","url":"https:\/\/video.twimg.com\/tweet_video\/FDInc58XMAoO3EV.mp4"}]},"sizes":{"thumb":{"w":
